vhdre/__init__.py
vhdre/__main__.py
vhdre-0.3.dist-info/LICENSE
vhdre-0.3.dist-info/METADATA
vhdre-0.3.dist-info/WHEEL
vhdre-0.3.dist-info/top_level.txt
vhdre-0.3.dist-info/RECORD
