Metadata-Version: 2.1
Name: vhdre
Version: 0.3
Summary: VHDL code generator for matching regular expressions.
Home-page: http://packages.python.org/vhdre
Author: Jeroen van Straten
Author-email: j.vanstraten-1@tudelft.nl
License: MIT
Keywords: vhdl regular expression generator
Platform: UNKNOWN
Classifier: Development Status :: 4 - Beta
Classifier: Topic :: Software Development :: Code Generators
Classifier: License :: OSI Approved :: MIT License
Requires-Dist: funcparserlib
